{
  "strategy_name": "10am vs 9:30am Price Compare",
  "strategy_version": "1.0.0",
  "configuration": {
    "symbol": "EURUSD",
    "start_date": "2025-11-05",
    "end_date": "2025-11-12",
    "timeframe": "30m",
    "stop_loss_pips": 15,
    "take_profit_pips": 25,
    "initial_balance": 10000,
    "risk_per_trade": 0.02,
    "max_open_trades": 1,
    "commission_per_trade": 0.0
  },
  "trades": [
    {
      "entry_time": "2025-11-12T17:54:00",
      "exit_time": "2025-11-12T19:33:00",
      "direction": "BUY",
      "entry_price": 1.15913,
      "exit_price": 1.1587,
      "pips": -4.299999999999304,
      "result": "EOD_CLOSE"
    }
  ],
  "summary": {
    "total_trades": 1,
    "winning_trades": 0,
    "losing_trades": 0,
    "win_rate": 0.0,
    "total_pips": -4.299999999999304,
    "profit_factor": 0.0,
    "average_win": 0.0,
    "average_loss": 0.0,
    "largest_win": 0.0,
    "largest_loss": 0.0
  },
  "risk_metrics": {
    "max_drawdown": 4.299999999999304,
    "max_consecutive_losses": 0,
    "max_consecutive_wins": 0
  },
  "execution": {
    "start_time": "2025-11-12T19:35:43.820471",
    "end_time": "2025-11-12T19:35:43.924374",
    "execution_time_seconds": 0.103903,
    "data_source": "InfluxDB (fresh)",
    "total_candles_processed": 100
  },
  "market_data": [
    {
      "timestamp": "2025-11-10T17:30:00",
      "open": 1.15481,
      "high": 1.15609,
      "low": 1.15476,
      "close": 1.15603,
      "volume": 2733.0
    },
    {
      "timestamp": "2025-11-10T18:00:00",
      "open": 1.15605,
      "high": 1.15648,
      "low": 1.15584,
      "close": 1.15594,
      "volume": 1988.0
    },
    {
      "timestamp": "2025-11-10T18:30:00",
      "open": 1.15596,
      "high": 1.15618,
      "low": 1.15576,
      "close": 1.15583,
      "volume": 1592.0
    },
    {
      "timestamp": "2025-11-10T19:00:00",
      "open": 1.15581,
      "high": 1.15627,
      "low": 1.15576,
      "close": 1.15618,
      "volume": 1646.0
    },
    {
      "timestamp": "2025-11-10T19:30:00",
      "open": 1.15617,
      "high": 1.15629,
      "low": 1.15592,
      "close": 1.15607,
      "volume": 1774.0
    },
    {
      "timestamp": "2025-11-10T20:00:00",
      "open": 1.15606,
      "high": 1.15629,
      "low": 1.15603,
      "close": 1.15627,
      "volume": 1562.0
    },
    {
      "timestamp": "2025-11-10T20:30:00",
      "open": 1.15625,
      "high": 1.15645,
      "low": 1.15622,
      "close": 1.15637,
      "volume": 1656.0
    },
    {
      "timestamp": "2025-11-10T21:00:00",
      "open": 1.15638,
      "high": 1.15639,
      "low": 1.15595,
      "close": 1.15595,
      "volume": 1079.0
    },
    {
      "timestamp": "2025-11-10T21:30:00",
      "open": 1.15596,
      "high": 1.15605,
      "low": 1.1555,
      "close": 1.15571,
      "volume": 1297.0
    },
    {
      "timestamp": "2025-11-10T22:00:00",
      "open": 1.15505,
      "high": 1.15574,
      "low": 1.15497,
      "close": 1.15567,
      "volume": 472.0
    },
    {
      "timestamp": "2025-11-10T22:30:00",
      "open": 1.15569,
      "high": 1.15581,
      "low": 1.15548,
      "close": 1.1556,
      "volume": 1039.0
    },
    {
      "timestamp": "2025-11-10T23:00:00",
      "open": 1.15568,
      "high": 1.15602,
      "low": 1.15558,
      "close": 1.15568,
      "volume": 1035.0
    },
    {
      "timestamp": "2025-11-10T23:30:00",
      "open": 1.15572,
      "high": 1.15597,
      "low": 1.15561,
      "close": 1.15565,
      "volume": 1008.0
    },
    {
      "timestamp": "2025-11-11T00:00:00",
      "open": 1.15567,
      "high": 1.15593,
      "low": 1.15558,
      "close": 1.15574,
      "volume": 1904.0
    },
    {
      "timestamp": "2025-11-11T00:30:00",
      "open": 1.15573,
      "high": 1.1558,
      "low": 1.15517,
      "close": 1.15521,
      "volume": 1864.0
    },
    {
      "timestamp": "2025-11-11T01:00:00",
      "open": 1.15522,
      "high": 1.15529,
      "low": 1.15468,
      "close": 1.15492,
      "volume": 2128.0
    },
    {
      "timestamp": "2025-11-11T01:30:00",
      "open": 1.15493,
      "high": 1.15546,
      "low": 1.15492,
      "close": 1.15544,
      "volume": 1930.0
    },
    {
      "timestamp": "2025-11-11T02:00:00",
      "open": 1.15545,
      "high": 1.15569,
      "low": 1.15541,
      "close": 1.15553,
      "volume": 1794.0
    },
    {
      "timestamp": "2025-11-11T02:30:00",
      "open": 1.15552,
      "high": 1.1556,
      "low": 1.15516,
      "close": 1.15532,
      "volume": 1462.0
    },
    {
      "timestamp": "2025-11-11T03:00:00",
      "open": 1.15531,
      "high": 1.15579,
      "low": 1.15531,
      "close": 1.15573,
      "volume": 1167.0
    },
    {
      "timestamp": "2025-11-11T03:30:00",
      "open": 1.15572,
      "high": 1.15578,
      "low": 1.1555,
      "close": 1.15562,
      "volume": 1188.0
    },
    {
      "timestamp": "2025-11-11T04:00:00",
      "open": 1.15561,
      "high": 1.1559,
      "low": 1.1555,
      "close": 1.15563,
      "volume": 1306.0
    },
    {
      "timestamp": "2025-11-11T04:30:00",
      "open": 1.15561,
      "high": 1.15591,
      "low": 1.15554,
      "close": 1.15577,
      "volume": 938.0
    },
    {
      "timestamp": "2025-11-11T05:00:00",
      "open": 1.15578,
      "high": 1.1565,
      "low": 1.15576,
      "close": 1.15629,
      "volume": 1416.0
    },
    {
      "timestamp": "2025-11-11T05:30:00",
      "open": 1.15628,
      "high": 1.15638,
      "low": 1.15607,
      "close": 1.15614,
      "volume": 1610.0
    },
    {
      "timestamp": "2025-11-11T06:00:00",
      "open": 1.15615,
      "high": 1.15628,
      "low": 1.15593,
      "close": 1.1561,
      "volume": 1220.0
    },
    {
      "timestamp": "2025-11-11T06:30:00",
      "open": 1.15609,
      "high": 1.15616,
      "low": 1.15502,
      "close": 1.15519,
      "volume": 1694.0
    },
    {
      "timestamp": "2025-11-11T07:00:00",
      "open": 1.15524,
      "high": 1.15562,
      "low": 1.15496,
      "close": 1.1555,
      "volume": 3255.0
    },
    {
      "timestamp": "2025-11-11T07:30:00",
      "open": 1.15549,
      "high": 1.15604,
      "low": 1.15537,
      "close": 1.15597,
      "volume": 3618.0
    },
    {
      "timestamp": "2025-11-11T08:00:00",
      "open": 1.15601,
      "high": 1.15682,
      "low": 1.15581,
      "close": 1.15637,
      "volume": 3057.0
    },
    {
      "timestamp": "2025-11-11T08:30:00",
      "open": 1.15636,
      "high": 1.15639,
      "low": 1.15541,
      "close": 1.15542,
      "volume": 2612.0
    },
    {
      "timestamp": "2025-11-11T09:00:00",
      "open": 1.15541,
      "high": 1.15644,
      "low": 1.15531,
      "close": 1.15635,
      "volume": 2860.0
    },
    {
      "timestamp": "2025-11-11T09:30:00",
      "open": 1.15636,
      "high": 1.15683,
      "low": 1.15636,
      "close": 1.15646,
      "volume": 2368.0
    },
    {
      "timestamp": "2025-11-11T10:00:00",
      "open": 1.15648,
      "high": 1.15727,
      "low": 1.15622,
      "close": 1.15716,
      "volume": 2536.0
    },
    {
      "timestamp": "2025-11-11T10:30:00",
      "open": 1.15715,
      "high": 1.15746,
      "low": 1.15695,
      "close": 1.15728,
      "volume": 2388.0
    },
    {
      "timestamp": "2025-11-11T11:00:00",
      "open": 1.15727,
      "high": 1.15776,
      "low": 1.15707,
      "close": 1.1573,
      "volume": 2531.0
    },
    {
      "timestamp": "2025-11-11T11:30:00",
      "open": 1.15727,
      "high": 1.15742,
      "low": 1.15698,
      "close": 1.15716,
      "volume": 2280.0
    },
    {
      "timestamp": "2025-11-11T12:00:00",
      "open": 1.15717,
      "high": 1.1577,
      "low": 1.15706,
      "close": 1.15721,
      "volume": 2491.0
    },
    {
      "timestamp": "2025-11-11T12:30:00",
      "open": 1.15722,
      "high": 1.15743,
      "low": 1.15682,
      "close": 1.15701,
      "volume": 2776.0
    },
    {
      "timestamp": "2025-11-11T13:00:00",
      "open": 1.15703,
      "high": 1.16005,
      "low": 1.15703,
      "close": 1.15948,
      "volume": 4694.0
    },
    {
      "timestamp": "2025-11-11T13:30:00",
      "open": 1.15946,
      "high": 1.16057,
      "low": 1.1593,
      "close": 1.16007,
      "volume": 4910.0
    },
    {
      "timestamp": "2025-11-11T14:00:00",
      "open": 1.16008,
      "high": 1.16046,
      "low": 1.15931,
      "close": 1.16012,
      "volume": 3615.0
    },
    {
      "timestamp": "2025-11-11T14:30:00",
      "open": 1.16016,
      "high": 1.16047,
      "low": 1.15985,
      "close": 1.16004,
      "volume": 3532.0
    },
    {
      "timestamp": "2025-11-11T15:00:00",
      "open": 1.16001,
      "high": 1.16029,
      "low": 1.15913,
      "close": 1.16021,
      "volume": 4138.0
    },
    {
      "timestamp": "2025-11-11T15:30:00",
      "open": 1.1602,
      "high": 1.1603,
      "low": 1.15919,
      "close": 1.15947,
      "volume": 3408.0
    },
    {
      "timestamp": "2025-11-11T16:00:00",
      "open": 1.15948,
      "high": 1.15997,
      "low": 1.15909,
      "close": 1.15933,
      "volume": 3094.0
    },
    {
      "timestamp": "2025-11-11T16:30:00",
      "open": 1.15932,
      "high": 1.15978,
      "low": 1.15903,
      "close": 1.15931,
      "volume": 2666.0
    },
    {
      "timestamp": "2025-11-11T17:00:00",
      "open": 1.15932,
      "high": 1.1598,
      "low": 1.15904,
      "close": 1.15974,
      "volume": 2180.0
    },
    {
      "timestamp": "2025-11-11T17:30:00",
      "open": 1.15973,
      "high": 1.15991,
      "low": 1.15944,
      "close": 1.1595,
      "volume": 1748.0
    },
    {
      "timestamp": "2025-11-11T18:00:00",
      "open": 1.15948,
      "high": 1.15954,
      "low": 1.15912,
      "close": 1.15929,
      "volume": 1732.0
    },
    {
      "timestamp": "2025-11-11T18:30:00",
      "open": 1.15928,
      "high": 1.15947,
      "low": 1.1591,
      "close": 1.15923,
      "volume": 1608.0
    },
    {
      "timestamp": "2025-11-11T19:00:00",
      "open": 1.15924,
      "high": 1.15928,
      "low": 1.15889,
      "close": 1.15909,
      "volume": 1704.0
    },
    {
      "timestamp": "2025-11-11T19:30:00",
      "open": 1.1591,
      "high": 1.15923,
      "low": 1.15831,
      "close": 1.15841,
      "volume": 1512.0
    },
    {
      "timestamp": "2025-11-11T20:00:00",
      "open": 1.15842,
      "high": 1.15888,
      "low": 1.15841,
      "close": 1.15858,
      "volume": 1708.0
    },
    {
      "timestamp": "2025-11-11T20:30:00",
      "open": 1.15856,
      "high": 1.15885,
      "low": 1.15829,
      "close": 1.1583,
      "volume": 1688.0
    },
    {
      "timestamp": "2025-11-11T21:00:00",
      "open": 1.15831,
      "high": 1.15854,
      "low": 1.15821,
      "close": 1.15834,
      "volume": 1533.0
    },
    {
      "timestamp": "2025-11-11T21:30:00",
      "open": 1.15835,
      "high": 1.15837,
      "low": 1.15809,
      "close": 1.15821,
      "volume": 1111.0
    },
    {
      "timestamp": "2025-11-11T22:00:00",
      "open": 1.15819,
      "high": 1.15841,
      "low": 1.15807,
      "close": 1.1582,
      "volume": 858.0
    },
    {
      "timestamp": "2025-11-11T22:30:00",
      "open": 1.15819,
      "high": 1.1585,
      "low": 1.15818,
      "close": 1.15848,
      "volume": 1159.0
    },
    {
      "timestamp": "2025-11-11T23:00:00",
      "open": 1.15846,
      "high": 1.15851,
      "low": 1.15819,
      "close": 1.15825,
      "volume": 750.0
    },
    {
      "timestamp": "2025-11-11T23:30:00",
      "open": 1.15826,
      "high": 1.1587,
      "low": 1.15826,
      "close": 1.15866,
      "volume": 764.0
    },
    {
      "timestamp": "2025-11-12T00:00:00",
      "open": 1.15864,
      "high": 1.15867,
      "low": 1.15827,
      "close": 1.15842,
      "volume": 1568.0
    },
    {
      "timestamp": "2025-11-12T00:30:00",
      "open": 1.15841,
      "high": 1.15851,
      "low": 1.15786,
      "close": 1.1579,
      "volume": 1720.0
    },
    {
      "timestamp": "2025-11-12T01:00:00",
      "open": 1.15789,
      "high": 1.1582,
      "low": 1.15758,
      "close": 1.15765,
      "volume": 2263.0
    },
    {
      "timestamp": "2025-11-12T01:30:00",
      "open": 1.15767,
      "high": 1.15788,
      "low": 1.15742,
      "close": 1.15752,
      "volume": 1478.0
    },
    {
      "timestamp": "2025-11-12T02:00:00",
      "open": 1.15751,
      "high": 1.15787,
      "low": 1.15751,
      "close": 1.1578,
      "volume": 1402.0
    },
    {
      "timestamp": "2025-11-12T02:30:00",
      "open": 1.15779,
      "high": 1.15795,
      "low": 1.1575,
      "close": 1.15786,
      "volume": 1511.0
    },
    {
      "timestamp": "2025-11-12T03:00:00",
      "open": 1.15787,
      "high": 1.15812,
      "low": 1.15753,
      "close": 1.15797,
      "volume": 1227.0
    },
    {
      "timestamp": "2025-11-12T03:30:00",
      "open": 1.15796,
      "high": 1.15799,
      "low": 1.15763,
      "close": 1.15773,
      "volume": 1015.0
    },
    {
      "timestamp": "2025-11-12T04:00:00",
      "open": 1.15772,
      "high": 1.15783,
      "low": 1.15712,
      "close": 1.15736,
      "volume": 1495.0
    },
    {
      "timestamp": "2025-11-12T04:30:00",
      "open": 1.15737,
      "high": 1.15742,
      "low": 1.15697,
      "close": 1.15718,
      "volume": 1620.0
    },
    {
      "timestamp": "2025-11-12T05:00:00",
      "open": 1.15719,
      "high": 1.15783,
      "low": 1.15708,
      "close": 1.15767,
      "volume": 2082.0
    },
    {
      "timestamp": "2025-11-12T05:30:00",
      "open": 1.15764,
      "high": 1.15784,
      "low": 1.1575,
      "close": 1.1576,
      "volume": 2202.0
    },
    {
      "timestamp": "2025-11-12T06:00:00",
      "open": 1.15759,
      "high": 1.158,
      "low": 1.15748,
      "close": 1.1579,
      "volume": 2118.0
    },
    {
      "timestamp": "2025-11-12T06:30:00",
      "open": 1.15792,
      "high": 1.15823,
      "low": 1.15782,
      "close": 1.15817,
      "volume": 1452.0
    },
    {
      "timestamp": "2025-11-12T07:00:00",
      "open": 1.1582,
      "high": 1.15883,
      "low": 1.1582,
      "close": 1.15857,
      "volume": 2450.0
    },
    {
      "timestamp": "2025-11-12T07:30:00",
      "open": 1.15858,
      "high": 1.15865,
      "low": 1.15809,
      "close": 1.15833,
      "volume": 2422.0
    },
    {
      "timestamp": "2025-11-12T08:00:00",
      "open": 1.15836,
      "high": 1.15867,
      "low": 1.15779,
      "close": 1.15855,
      "volume": 3036.0
    },
    {
      "timestamp": "2025-11-12T08:30:00",
      "open": 1.15851,
      "high": 1.15877,
      "low": 1.15766,
      "close": 1.15769,
      "volume": 3296.0
    },
    {
      "timestamp": "2025-11-12T09:00:00",
      "open": 1.1577,
      "high": 1.15802,
      "low": 1.15723,
      "close": 1.15735,
      "volume": 3338.0
    },
    {
      "timestamp": "2025-11-12T09:30:00",
      "open": 1.15733,
      "high": 1.15768,
      "low": 1.15679,
      "close": 1.15698,
      "volume": 2900.0
    },
    {
      "timestamp": "2025-11-12T10:00:00",
      "open": 1.15697,
      "high": 1.15753,
      "low": 1.15651,
      "close": 1.15657,
      "volume": 3070.0
    },
    {
      "timestamp": "2025-11-12T10:30:00",
      "open": 1.15658,
      "high": 1.15722,
      "low": 1.15648,
      "close": 1.15699,
      "volume": 2636.0
    },
    {
      "timestamp": "2025-11-12T11:00:00",
      "open": 1.15701,
      "high": 1.15721,
      "low": 1.15654,
      "close": 1.15706,
      "volume": 2078.0
    },
    {
      "timestamp": "2025-11-12T11:30:00",
      "open": 1.15709,
      "high": 1.15776,
      "low": 1.15706,
      "close": 1.15776,
      "volume": 2646.0
    },
    {
      "timestamp": "2025-11-12T12:00:00",
      "open": 1.15775,
      "high": 1.15803,
      "low": 1.1574,
      "close": 1.15767,
      "volume": 3034.0
    },
    {
      "timestamp": "2025-11-12T12:30:00",
      "open": 1.1577,
      "high": 1.15792,
      "low": 1.15712,
      "close": 1.15767,
      "volume": 3464.0
    },
    {
      "timestamp": "2025-11-12T13:00:00",
      "open": 1.15766,
      "high": 1.15797,
      "low": 1.15696,
      "close": 1.157,
      "volume": 3522.0
    },
    {
      "timestamp": "2025-11-12T13:30:00",
      "open": 1.15699,
      "high": 1.15724,
      "low": 1.15658,
      "close": 1.1572,
      "volume": 3478.0
    },
    {
      "timestamp": "2025-11-12T14:00:00",
      "open": 1.15719,
      "high": 1.1575,
      "low": 1.15628,
      "close": 1.15642,
      "volume": 3736.0
    },
    {
      "timestamp": "2025-11-12T14:30:00",
      "open": 1.15643,
      "high": 1.15755,
      "low": 1.15638,
      "close": 1.15753,
      "volume": 4093.0
    },
    {
      "timestamp": "2025-11-12T15:00:00",
      "open": 1.15751,
      "high": 1.15834,
      "low": 1.15727,
      "close": 1.15771,
      "volume": 4049.0
    },
    {
      "timestamp": "2025-11-12T15:30:00",
      "open": 1.1577,
      "high": 1.15956,
      "low": 1.15762,
      "close": 1.15937,
      "volume": 4004.0
    },
    {
      "timestamp": "2025-11-12T16:00:00",
      "open": 1.15936,
      "high": 1.15975,
      "low": 1.15905,
      "close": 1.1591,
      "volume": 4092.0
    },
    {
      "timestamp": "2025-11-12T16:30:00",
      "open": 1.15911,
      "high": 1.15947,
      "low": 1.15879,
      "close": 1.15908,
      "volume": 3044.0
    },
    {
      "timestamp": "2025-11-12T17:00:00",
      "open": 1.1591,
      "high": 1.15969,
      "low": 1.15907,
      "close": 1.15931,
      "volume": 2573.0
    },
    {
      "timestamp": "2025-11-12T17:30:00",
      "open": 1.1593,
      "high": 1.15957,
      "low": 1.15912,
      "close": 1.15927,
      "volume": 1847.0
    },
    {
      "timestamp": "2025-11-12T18:00:00",
      "open": 1.15928,
      "high": 1.1594,
      "low": 1.15908,
      "close": 1.15924,
      "volume": 1804.0
    },
    {
      "timestamp": "2025-11-12T18:30:00",
      "open": 1.15926,
      "high": 1.15941,
      "low": 1.15886,
      "close": 1.15891,
      "volume": 1542.0
    },
    {
      "timestamp": "2025-11-12T19:00:00",
      "open": 1.15892,
      "high": 1.15901,
      "low": 1.15839,
      "close": 1.15854,
      "volume": 1750.0
    }
  ]
}